rgle_arapm/__init__.py
rgle_arapm/arapm.py
rgle_arapm-0.0.2.dist-info/METADATA
rgle_arapm-0.0.2.dist-info/WHEEL
rgle_arapm-0.0.2.dist-info/top_level.txt
rgle_arapm-0.0.2.dist-info/RECORD
